extract_model/__init__.py
extract_model/_version.py
extract_model/accessor.py
extract_model/extract_model.py
extract_model/model_type.py
extract_model/preprocessing.py
extract_model/sorting.py
extract_model/utils.py
extract_model/grids/__init__.py
extract_model/grids/triangular_mesh.py
extract_model/xr/__init__.py
extract_model/xr/triangular_mesh_netcdf.py
extract_model-1.4.4.dist-info/licenses/LICENSE.txt
tests/__init__.py
tests/make_test_datasets.py
tests/test_accessor.py
tests/test_datasets.py
tests/test_em.py
tests/test_sel2d.py
tests/test_sorting.py
tests/test_utils.py
tests/utils.py
tests/xr/__init__.py
tests/xr/test_triangular_mesh_netcdf.py
extract_model-1.4.4.dist-info/METADATA
extract_model-1.4.4.dist-info/WHEEL
extract_model-1.4.4.dist-info/entry_points.txt
extract_model-1.4.4.dist-info/top_level.txt
extract_model-1.4.4.dist-info/RECORD
