Metadata-Version: 2.4
Name: extract_model
Version: 1.4.4
Summary: Facilitates read-in and extraction for ocean model output.
Home-page: https://github.com/axiom-data-science/extract_model
Author: Kristen Thyng
Author-email: kristen@axds.co
License: MIT
Classifier: Development Status :: 3 - Alpha
Classifier: Topic :: Scientific/Engineering
Classifier: Intended Audience :: Science/Research
Classifier: Operating System :: OS Independent
Classifier: Programming Language :: Python
Classifier: Programming Language :: Python :: 3
Classifier: Programming Language :: Python :: 3.11
Classifier: Programming Language :: Python :: 3.12
Classifier: Programming Language :: Python :: 3.13
Classifier: License :: OSI Approved :: MIT License
Requires-Python: >=3.8
License-File: LICENSE.txt
Requires-Dist: cf_xarray
Requires-Dist: dask
Requires-Dist: netcdf4
Requires-Dist: numpy
Requires-Dist: pip
Requires-Dist: scikit-learn
Requires-Dist: xarray
Dynamic: license-file
